{
    "env": {
        "myDefaultIncludePath": [
            "${workspaceFolder}",
            "${workspaceFolder}/include"
        ]
    },
    "configurations": [
        {
            "name": "Linux",
            "includePath": [
                "${default}",
                "/usr/include/**",
                "/home/office/src/vcpkg/packages/**",
                "${workspaceFolder}/**",
                "/usr/include/qt5/**"
            ],
            "defines": [],
            "compilerPath": "/usr/bin/clang",
            "intelliSenseMode": "linux-clang-x64",
            "configurationProvider": "go2sh.cmake-integration"
        }
    ],
    "version": 4
}